<?xml version="1.0" encoding="UTF-8"?>
<dataset>
<BattleConfigTemplate configId="1" autoFight="1" soundID="0" preDesc="520001" />
<BattleConfigTemplate configId="2" autoFight="1" soundID="0" preDesc="520002" />
<BattleConfigTemplate configId="3" autoFight="1" soundID="0" preDesc="520003" />
<BattleConfigTemplate configId="4" autoFight="1" soundID="0" preDesc="520004" />
<BattleConfigTemplate configId="600" autoFight="0" soundID="100201" preDesc="520600" />
<BattleConfigTemplate configId="900" autoFight="0" soundID="100101" preDesc="520900" />
<BattleConfigTemplate configId="100001" autoFight="1" soundID="100101" preDesc="530001" />
<BattleConfigTemplate configId="100101" autoFight="1" soundID="100100" preDesc="530101" />
<BattleConfigTemplate configId="100102" autoFight="1" soundID="100103" preDesc="530102" />
<BattleConfigTemplate configId="100103" autoFight="1" soundID="100201" preDesc="530103" />
<BattleConfigTemplate configId="100104" autoFight="0" soundID="100100" preDesc="530104" />
<BattleConfigTemplate configId="100105" autoFight="1" soundID="100103" preDesc="530105" />
<BattleConfigTemplate configId="100106" autoFight="1" soundID="100100" preDesc="530106" />
<BattleConfigTemplate configId="100107" autoFight="1" soundID="100200" preDesc="530107" />
<BattleConfigTemplate configId="100201" autoFight="1" soundID="10000" preDesc="530201" />
<BattleConfigTemplate configId="100202" autoFight="0" soundID="100101" preDesc="530202" />
<BattleConfigTemplate configId="100203" autoFight="1" soundID="100200" preDesc="530203" />
<BattleConfigTemplate configId="100204" autoFight="1" soundID="100102" preDesc="530204" />
<BattleConfigTemplate configId="100205" autoFight="1" soundID="10000" preDesc="530205" />
<BattleConfigTemplate configId="100206" autoFight="1" soundID="100110" preDesc="530206" />
<BattleConfigTemplate configId="100207" autoFight="1" soundID="100200" preDesc="530207" />
<BattleConfigTemplate configId="100301" autoFight="1" soundID="100100" preDesc="530301" />
<BattleConfigTemplate configId="100302" autoFight="1" soundID="100101" preDesc="530302" />
<BattleConfigTemplate configId="100303" autoFight="1" soundID="100110" preDesc="530303" />
<BattleConfigTemplate configId="100304" autoFight="1" soundID="100100" preDesc="530304" />
<BattleConfigTemplate configId="100305" autoFight="1" soundID="100101" preDesc="530305" />
<BattleConfigTemplate configId="100306" autoFight="1" soundID="100110" preDesc="530306" />
<BattleConfigTemplate configId="100307" autoFight="1" soundID="100200" preDesc="530307" />
<BattleConfigTemplate configId="100401" autoFight="1" soundID="100103" preDesc="530401" />
<BattleConfigTemplate configId="100402" autoFight="1" soundID="100102" preDesc="530402" />
<BattleConfigTemplate configId="100403" autoFight="1" soundID="100101" preDesc="530403" />
<BattleConfigTemplate configId="100404" autoFight="1" soundID="100100" preDesc="530404" />
<BattleConfigTemplate configId="100405" autoFight="1" soundID="100101" preDesc="530405" />
<BattleConfigTemplate configId="100406" autoFight="1" soundID="100100" preDesc="530406" />
<BattleConfigTemplate configId="100407" autoFight="1" soundID="100100" preDesc="530407" />
<BattleConfigTemplate configId="100408" autoFight="1" soundID="100100" preDesc="530408" />
<BattleConfigTemplate configId="100409" autoFight="1" soundID="100101" preDesc="530409" />
<BattleConfigTemplate configId="100501" autoFight="1" soundID="100103" preDesc="530501" />
<BattleConfigTemplate configId="100502" autoFight="1" soundID="100102" preDesc="530502" />
<BattleConfigTemplate configId="100503" autoFight="1" soundID="100101" preDesc="530503" />
<BattleConfigTemplate configId="100504" autoFight="1" soundID="100100" preDesc="530504" />
<BattleConfigTemplate configId="100505" autoFight="1" soundID="100100" preDesc="530505" />
<BattleConfigTemplate configId="100506" autoFight="1" soundID="100102" preDesc="530506" />
<BattleConfigTemplate configId="100507" autoFight="1" soundID="100100" preDesc="530507" />
<BattleConfigTemplate configId="100508" autoFight="1" soundID="100100" preDesc="530508" />
<BattleConfigTemplate configId="100509" autoFight="1" soundID="100101" preDesc="530509" />
<BattleConfigTemplate configId="100601" autoFight="1" soundID="100100" preDesc="530601" />
<BattleConfigTemplate configId="100602" autoFight="1" soundID="100100" preDesc="530602" />
<BattleConfigTemplate configId="100603" autoFight="1" soundID="100101" preDesc="530603" />
<BattleConfigTemplate configId="100604" autoFight="1" soundID="100100" preDesc="530604" />
<BattleConfigTemplate configId="100605" autoFight="1" soundID="100100" preDesc="530605" />
<BattleConfigTemplate configId="100606" autoFight="1" soundID="100101" preDesc="530606" />
<BattleConfigTemplate configId="100607" autoFight="1" soundID="100100" preDesc="530607" />
<BattleConfigTemplate configId="100608" autoFight="1" soundID="100100" preDesc="530608" />
<BattleConfigTemplate configId="100609" autoFight="1" soundID="100101" preDesc="530609" />
<BattleConfigTemplate configId="100701" autoFight="1" soundID="100100" preDesc="530701" />
<BattleConfigTemplate configId="100702" autoFight="1" soundID="100102" preDesc="530702" />
<BattleConfigTemplate configId="100703" autoFight="1" soundID="100101" preDesc="530703" />
<BattleConfigTemplate configId="100704" autoFight="1" soundID="100100" preDesc="530704" />
<BattleConfigTemplate configId="100705" autoFight="1" soundID="100100" preDesc="530705" />
<BattleConfigTemplate configId="100706" autoFight="1" soundID="100101" preDesc="530706" />
<BattleConfigTemplate configId="100707" autoFight="1" soundID="100100" preDesc="530707" />
<BattleConfigTemplate configId="100708" autoFight="1" soundID="100100" preDesc="530708" />
<BattleConfigTemplate configId="100709" autoFight="1" soundID="100101" preDesc="530709" />
<BattleConfigTemplate configId="100801" autoFight="1" soundID="100201" preDesc="530801" />
<BattleConfigTemplate configId="100802" autoFight="1" soundID="100100" preDesc="530802" />
<BattleConfigTemplate configId="100803" autoFight="1" soundID="100101" preDesc="530803" />
<BattleConfigTemplate configId="100804" autoFight="1" soundID="100102" preDesc="530804" />
<BattleConfigTemplate configId="100805" autoFight="1" soundID="100100" preDesc="530805" />
<BattleConfigTemplate configId="100806" autoFight="1" soundID="100102" preDesc="530806" />
<BattleConfigTemplate configId="100807" autoFight="1" soundID="100100" preDesc="530807" />
<BattleConfigTemplate configId="100808" autoFight="1" soundID="100100" preDesc="530808" />
<BattleConfigTemplate configId="100809" autoFight="1" soundID="100101" preDesc="530809" />
<BattleConfigTemplate configId="100901" autoFight="1" soundID="100102" preDesc="530901" />
<BattleConfigTemplate configId="100902" autoFight="1" soundID="100100" preDesc="530902" />
<BattleConfigTemplate configId="100903" autoFight="1" soundID="100101" preDesc="530903" />
<BattleConfigTemplate configId="100904" autoFight="1" soundID="100201" preDesc="530904" />
<BattleConfigTemplate configId="100905" autoFight="1" soundID="100102" preDesc="530905" />
<BattleConfigTemplate configId="100906" autoFight="1" soundID="100101" preDesc="530906" />
<BattleConfigTemplate configId="100907" autoFight="1" soundID="100100" preDesc="530907" />
<BattleConfigTemplate configId="100908" autoFight="1" soundID="100100" preDesc="530908" />
<BattleConfigTemplate configId="100909" autoFight="1" soundID="100101" preDesc="530909" />
<BattleConfigTemplate configId="101001" autoFight="1" soundID="100100" preDesc="531001" />
<BattleConfigTemplate configId="101002" autoFight="1" soundID="100100" preDesc="531002" />
<BattleConfigTemplate configId="101003" autoFight="1" soundID="100100" preDesc="531003" />
<BattleConfigTemplate configId="101004" autoFight="1" soundID="100201" preDesc="531004" />
<BattleConfigTemplate configId="101005" autoFight="1" soundID="100100" preDesc="531005" />
<BattleConfigTemplate configId="101006" autoFight="1" soundID="100102" preDesc="531006" />
<BattleConfigTemplate configId="101007" autoFight="1" soundID="100100" preDesc="531007" />
<BattleConfigTemplate configId="101008" autoFight="1" soundID="100100" preDesc="531008" />
<BattleConfigTemplate configId="101009" autoFight="1" soundID="100101" preDesc="531009" />
<BattleConfigTemplate configId="101101" autoFight="1" soundID="100102" preDesc="531101" />
<BattleConfigTemplate configId="101102" autoFight="1" soundID="100100" preDesc="531102" />
<BattleConfigTemplate configId="101103" autoFight="1" soundID="100100" preDesc="531103" />
<BattleConfigTemplate configId="101104" autoFight="1" soundID="100100" preDesc="531104" />
<BattleConfigTemplate configId="101105" autoFight="1" soundID="100100" preDesc="531105" />
<BattleConfigTemplate configId="101106" autoFight="1" soundID="100100" preDesc="531106" />
<BattleConfigTemplate configId="101107" autoFight="1" soundID="100100" preDesc="531107" />
<BattleConfigTemplate configId="101108" autoFight="1" soundID="100100" preDesc="531108" />
<BattleConfigTemplate configId="101109" autoFight="1" soundID="100101" preDesc="531109" />
<BattleConfigTemplate configId="101201" autoFight="1" soundID="100100" preDesc="531201" />
<BattleConfigTemplate configId="101202" autoFight="1" soundID="100100" preDesc="531202" />
<BattleConfigTemplate configId="101203" autoFight="1" soundID="100100" preDesc="531203" />
<BattleConfigTemplate configId="101204" autoFight="1" soundID="100100" preDesc="531204" />
<BattleConfigTemplate configId="101205" autoFight="1" soundID="100100" preDesc="531205" />
<BattleConfigTemplate configId="101206" autoFight="1" soundID="100100" preDesc="531206" />
<BattleConfigTemplate configId="101207" autoFight="1" soundID="100100" preDesc="531207" />
<BattleConfigTemplate configId="101208" autoFight="1" soundID="100100" preDesc="531208" />
<BattleConfigTemplate configId="101209" autoFight="1" soundID="100203" preDesc="531209" />
<BattleConfigTemplate configId="101301" autoFight="1" soundID="100100" preDesc="531301" />
<BattleConfigTemplate configId="101302" autoFight="1" soundID="100103" preDesc="531302" />
<BattleConfigTemplate configId="101303" autoFight="1" soundID="100103" preDesc="531303" />
<BattleConfigTemplate configId="101304" autoFight="1" soundID="100201" preDesc="531304" />
<BattleConfigTemplate configId="101305" autoFight="1" soundID="100201" preDesc="531305" />
<BattleConfigTemplate configId="101306" autoFight="1" soundID="100100" preDesc="531306" />
<BattleConfigTemplate configId="101307" autoFight="1" soundID="100100" preDesc="531307" />
<BattleConfigTemplate configId="101308" autoFight="1" soundID="100100" preDesc="531308" />
<BattleConfigTemplate configId="101309" autoFight="1" soundID="100203" preDesc="531309" />
<BattleConfigTemplate configId="101401" autoFight="1" soundID="100100" preDesc="531401" />
<BattleConfigTemplate configId="101402" autoFight="1" soundID="100103" preDesc="531402" />
<BattleConfigTemplate configId="101403" autoFight="1" soundID="100103" preDesc="531403" />
<BattleConfigTemplate configId="101404" autoFight="1" soundID="100201" preDesc="531404" />
<BattleConfigTemplate configId="101405" autoFight="1" soundID="100201" preDesc="531405" />
<BattleConfigTemplate configId="101406" autoFight="1" soundID="100100" preDesc="531406" />
<BattleConfigTemplate configId="101407" autoFight="1" soundID="100100" preDesc="531407" />
<BattleConfigTemplate configId="101408" autoFight="1" soundID="100100" preDesc="531408" />
<BattleConfigTemplate configId="101409" autoFight="1" soundID="100203" preDesc="531409" />
<BattleConfigTemplate configId="101501" autoFight="1" soundID="100100" preDesc="531501" />
<BattleConfigTemplate configId="101502" autoFight="1" soundID="100103" preDesc="531502" />
<BattleConfigTemplate configId="101503" autoFight="1" soundID="100103" preDesc="531503" />
<BattleConfigTemplate configId="101504" autoFight="1" soundID="100201" preDesc="531504" />
<BattleConfigTemplate configId="101505" autoFight="1" soundID="100201" preDesc="531505" />
<BattleConfigTemplate configId="101506" autoFight="1" soundID="100100" preDesc="531506" />
<BattleConfigTemplate configId="101507" autoFight="1" soundID="100100" preDesc="531507" />
<BattleConfigTemplate configId="101508" autoFight="1" soundID="100100" preDesc="531508" />
<BattleConfigTemplate configId="101509" autoFight="1" soundID="100203" preDesc="531509" />
<BattleConfigTemplate configId="101601" autoFight="1" soundID="100100" preDesc="531601" />
<BattleConfigTemplate configId="101602" autoFight="1" soundID="100103" preDesc="531602" />
<BattleConfigTemplate configId="101603" autoFight="1" soundID="100103" preDesc="531603" />
<BattleConfigTemplate configId="101604" autoFight="1" soundID="100201" preDesc="531604" />
<BattleConfigTemplate configId="101605" autoFight="1" soundID="100201" preDesc="531605" />
<BattleConfigTemplate configId="101606" autoFight="1" soundID="100100" preDesc="531606" />
<BattleConfigTemplate configId="101607" autoFight="1" soundID="100100" preDesc="531607" />
<BattleConfigTemplate configId="101608" autoFight="1" soundID="100100" preDesc="531608" />
<BattleConfigTemplate configId="101609" autoFight="1" soundID="100203" preDesc="531609" />
<BattleConfigTemplate configId="101701" autoFight="1" soundID="100100" preDesc="531701" />
<BattleConfigTemplate configId="101702" autoFight="1" soundID="100103" preDesc="531702" />
<BattleConfigTemplate configId="101703" autoFight="1" soundID="100103" preDesc="531703" />
<BattleConfigTemplate configId="101704" autoFight="1" soundID="100201" preDesc="531704" />
<BattleConfigTemplate configId="101705" autoFight="1" soundID="100201" preDesc="531705" />
<BattleConfigTemplate configId="101706" autoFight="1" soundID="100100" preDesc="531706" />
<BattleConfigTemplate configId="101707" autoFight="1" soundID="100100" preDesc="531707" />
<BattleConfigTemplate configId="101708" autoFight="1" soundID="100100" preDesc="531708" />
<BattleConfigTemplate configId="101709" autoFight="1" soundID="100203" preDesc="531709" />
<BattleConfigTemplate configId="101801" autoFight="1" soundID="100100" preDesc="531801" />
<BattleConfigTemplate configId="101802" autoFight="1" soundID="100103" preDesc="531802" />
<BattleConfigTemplate configId="101803" autoFight="1" soundID="100103" preDesc="531803" />
<BattleConfigTemplate configId="101804" autoFight="1" soundID="100201" preDesc="531804" />
<BattleConfigTemplate configId="101805" autoFight="1" soundID="100201" preDesc="531805" />
<BattleConfigTemplate configId="101806" autoFight="1" soundID="100100" preDesc="531806" />
<BattleConfigTemplate configId="101807" autoFight="1" soundID="100100" preDesc="531807" />
<BattleConfigTemplate configId="101808" autoFight="1" soundID="100100" preDesc="531808" />
<BattleConfigTemplate configId="101809" autoFight="1" soundID="100203" preDesc="531809" />
<BattleConfigTemplate configId="101901" autoFight="1" soundID="100100" preDesc="531901" />
<BattleConfigTemplate configId="101902" autoFight="1" soundID="100103" preDesc="531902" />
<BattleConfigTemplate configId="101903" autoFight="1" soundID="100103" preDesc="531903" />
<BattleConfigTemplate configId="101904" autoFight="1" soundID="100201" preDesc="531904" />
<BattleConfigTemplate configId="101905" autoFight="1" soundID="100201" preDesc="531905" />
<BattleConfigTemplate configId="101906" autoFight="1" soundID="100100" preDesc="531906" />
<BattleConfigTemplate configId="101907" autoFight="1" soundID="100100" preDesc="531907" />
<BattleConfigTemplate configId="101908" autoFight="1" soundID="100100" preDesc="531908" />
<BattleConfigTemplate configId="101909" autoFight="1" soundID="100203" preDesc="531909" />
<BattleConfigTemplate configId="102001" autoFight="1" soundID="100100" preDesc="532001" />
<BattleConfigTemplate configId="102002" autoFight="1" soundID="100103" preDesc="532002" />
<BattleConfigTemplate configId="102003" autoFight="1" soundID="100103" preDesc="532003" />
<BattleConfigTemplate configId="102004" autoFight="1" soundID="100201" preDesc="532004" />
<BattleConfigTemplate configId="102005" autoFight="1" soundID="100201" preDesc="532005" />
<BattleConfigTemplate configId="102006" autoFight="1" soundID="100100" preDesc="532006" />
<BattleConfigTemplate configId="102007" autoFight="1" soundID="100100" preDesc="532007" />
<BattleConfigTemplate configId="102008" autoFight="1" soundID="100100" preDesc="532008" />
<BattleConfigTemplate configId="102009" autoFight="1" soundID="100203" preDesc="532009" />
<BattleConfigTemplate configId="102101" autoFight="1" soundID="100100" preDesc="532101" />
<BattleConfigTemplate configId="102102" autoFight="1" soundID="100103" preDesc="532102" />
<BattleConfigTemplate configId="102103" autoFight="1" soundID="100103" preDesc="532103" />
<BattleConfigTemplate configId="102104" autoFight="1" soundID="100201" preDesc="532104" />
<BattleConfigTemplate configId="102105" autoFight="1" soundID="100201" preDesc="532105" />
<BattleConfigTemplate configId="102106" autoFight="1" soundID="100100" preDesc="532106" />
<BattleConfigTemplate configId="102107" autoFight="1" soundID="100100" preDesc="532107" />
<BattleConfigTemplate configId="102108" autoFight="1" soundID="100100" preDesc="532108" />
<BattleConfigTemplate configId="102109" autoFight="1" soundID="100203" preDesc="532109" />
<BattleConfigTemplate configId="102201" autoFight="1" soundID="100100" preDesc="532201" />
<BattleConfigTemplate configId="102202" autoFight="1" soundID="100103" preDesc="532202" />
<BattleConfigTemplate configId="102203" autoFight="1" soundID="100103" preDesc="532203" />
<BattleConfigTemplate configId="102204" autoFight="1" soundID="100201" preDesc="532204" />
<BattleConfigTemplate configId="102205" autoFight="1" soundID="100201" preDesc="532205" />
<BattleConfigTemplate configId="102206" autoFight="1" soundID="100100" preDesc="532206" />
<BattleConfigTemplate configId="102207" autoFight="1" soundID="100100" preDesc="532207" />
<BattleConfigTemplate configId="102208" autoFight="1" soundID="100100" preDesc="532208" />
<BattleConfigTemplate configId="102209" autoFight="1" soundID="100203" preDesc="532209" />
<BattleConfigTemplate configId="102301" autoFight="1" soundID="100100" preDesc="532301" />
<BattleConfigTemplate configId="102302" autoFight="1" soundID="100103" preDesc="532302" />
<BattleConfigTemplate configId="102303" autoFight="1" soundID="100103" preDesc="532303" />
<BattleConfigTemplate configId="102304" autoFight="1" soundID="100201" preDesc="532304" />
<BattleConfigTemplate configId="102305" autoFight="1" soundID="100201" preDesc="532305" />
<BattleConfigTemplate configId="102306" autoFight="1" soundID="100100" preDesc="532306" />
<BattleConfigTemplate configId="102307" autoFight="1" soundID="100100" preDesc="532307" />
<BattleConfigTemplate configId="102308" autoFight="1" soundID="100100" preDesc="532308" />
<BattleConfigTemplate configId="102309" autoFight="1" soundID="100203" preDesc="532309" />
<BattleConfigTemplate configId="102401" autoFight="1" soundID="100100" preDesc="532401" />
<BattleConfigTemplate configId="102402" autoFight="1" soundID="100103" preDesc="532402" />
<BattleConfigTemplate configId="102403" autoFight="1" soundID="100103" preDesc="532403" />
<BattleConfigTemplate configId="102404" autoFight="1" soundID="100201" preDesc="532404" />
<BattleConfigTemplate configId="102405" autoFight="1" soundID="100201" preDesc="532405" />
<BattleConfigTemplate configId="102406" autoFight="1" soundID="100100" preDesc="532406" />
<BattleConfigTemplate configId="102407" autoFight="1" soundID="100100" preDesc="532407" />
<BattleConfigTemplate configId="102408" autoFight="1" soundID="100100" preDesc="532408" />
<BattleConfigTemplate configId="102409" autoFight="1" soundID="100203" preDesc="532409" />
<BattleConfigTemplate configId="200001" autoFight="1" soundID="100200" preDesc="540001" />
<BattleConfigTemplate configId="200002" autoFight="1" soundID="100200" preDesc="540002" />
<BattleConfigTemplate configId="200003" autoFight="1" soundID="100200" preDesc="540003" />
<BattleConfigTemplate configId="200004" autoFight="1" soundID="100200" preDesc="540004" />
<BattleConfigTemplate configId="200005" autoFight="1" soundID="100200" preDesc="540005" />
<BattleConfigTemplate configId="200006" autoFight="1" soundID="100200" preDesc="540006" />
<BattleConfigTemplate configId="200007" autoFight="1" soundID="100200" preDesc="540007" />
<BattleConfigTemplate configId="200008" autoFight="1" soundID="100200" preDesc="540008" />
<BattleConfigTemplate configId="200009" autoFight="1" soundID="100200" preDesc="540009" />
<BattleConfigTemplate configId="200010" autoFight="1" soundID="100200" preDesc="540010" />
<BattleConfigTemplate configId="200011" autoFight="1" soundID="100200" preDesc="540011" />
<BattleConfigTemplate configId="200012" autoFight="1" soundID="100200" preDesc="540012" />
<BattleConfigTemplate configId="200013" autoFight="1" soundID="100200" preDesc="540013" />
<BattleConfigTemplate configId="200014" autoFight="1" soundID="100200" preDesc="540014" />
<BattleConfigTemplate configId="200015" autoFight="1" soundID="100200" preDesc="540015" />
<BattleConfigTemplate configId="200016" autoFight="1" soundID="100200" preDesc="540016" />
<BattleConfigTemplate configId="200017" autoFight="1" soundID="100200" preDesc="540017" />
<BattleConfigTemplate configId="200018" autoFight="1" soundID="100200" preDesc="540018" />
<BattleConfigTemplate configId="200019" autoFight="1" soundID="100200" preDesc="540019" />
<BattleConfigTemplate configId="200020" autoFight="1" soundID="100200" preDesc="540020" />
<BattleConfigTemplate configId="200021" autoFight="1" soundID="100200" preDesc="540021" />
<BattleConfigTemplate configId="200022" autoFight="1" soundID="100200" preDesc="540022" />
<BattleConfigTemplate configId="200023" autoFight="1" soundID="100200" preDesc="540023" />
<BattleConfigTemplate configId="200024" autoFight="1" soundID="100200" preDesc="540024" />
<BattleConfigTemplate configId="200025" autoFight="1" soundID="100200" preDesc="540025" />
<BattleConfigTemplate configId="200026" autoFight="1" soundID="100200" preDesc="540026" />
<BattleConfigTemplate configId="200027" autoFight="1" soundID="100200" preDesc="540027" />
<BattleConfigTemplate configId="200028" autoFight="1" soundID="100200" preDesc="540028" />
<BattleConfigTemplate configId="300101" autoFight="1" soundID="100103" preDesc="550101" />
<BattleConfigTemplate configId="300102" autoFight="1" soundID="100103" preDesc="550102" />
<BattleConfigTemplate configId="300103" autoFight="1" soundID="100103" preDesc="550103" />
<BattleConfigTemplate configId="300104" autoFight="1" soundID="100103" preDesc="550104" />
<BattleConfigTemplate configId="300105" autoFight="1" soundID="100103" preDesc="550105" />
<BattleConfigTemplate configId="300106" autoFight="1" soundID="100103" preDesc="550106" />
<BattleConfigTemplate configId="300107" autoFight="1" soundID="100103" preDesc="550107" />
<BattleConfigTemplate configId="300108" autoFight="1" soundID="100103" preDesc="550108" />
<BattleConfigTemplate configId="300109" autoFight="1" soundID="100103" preDesc="550109" />
<BattleConfigTemplate configId="300110" autoFight="1" soundID="100103" preDesc="550110" />
<BattleConfigTemplate configId="300201" autoFight="1" soundID="100103" preDesc="550201" />
<BattleConfigTemplate configId="300202" autoFight="1" soundID="100103" preDesc="550202" />
<BattleConfigTemplate configId="300203" autoFight="1" soundID="100103" preDesc="550203" />
<BattleConfigTemplate configId="300204" autoFight="1" soundID="100103" preDesc="550204" />
<BattleConfigTemplate configId="300205" autoFight="1" soundID="100103" preDesc="550205" />
<BattleConfigTemplate configId="300206" autoFight="1" soundID="100103" preDesc="550206" />
<BattleConfigTemplate configId="300207" autoFight="1" soundID="100103" preDesc="550207" />
<BattleConfigTemplate configId="300208" autoFight="1" soundID="100103" preDesc="550208" />
<BattleConfigTemplate configId="300209" autoFight="1" soundID="100103" preDesc="550209" />
<BattleConfigTemplate configId="300210" autoFight="1" soundID="100103" preDesc="550210" />
<BattleConfigTemplate configId="300301" autoFight="1" soundID="100103" preDesc="550301" />
<BattleConfigTemplate configId="300302" autoFight="1" soundID="100103" preDesc="550302" />
<BattleConfigTemplate configId="300303" autoFight="1" soundID="100103" preDesc="550303" />
<BattleConfigTemplate configId="300304" autoFight="1" soundID="100103" preDesc="550304" />
<BattleConfigTemplate configId="300305" autoFight="1" soundID="100103" preDesc="550305" />
<BattleConfigTemplate configId="300306" autoFight="1" soundID="100103" preDesc="550306" />
<BattleConfigTemplate configId="300307" autoFight="1" soundID="100103" preDesc="550307" />
<BattleConfigTemplate configId="300308" autoFight="1" soundID="100103" preDesc="550308" />
<BattleConfigTemplate configId="300309" autoFight="1" soundID="100103" preDesc="550309" />
<BattleConfigTemplate configId="300310" autoFight="1" soundID="100103" preDesc="550310" />
<BattleConfigTemplate configId="300401" autoFight="1" soundID="100103" preDesc="550401" />
<BattleConfigTemplate configId="300402" autoFight="1" soundID="100103" preDesc="550402" />
<BattleConfigTemplate configId="300403" autoFight="1" soundID="100103" preDesc="550403" />
<BattleConfigTemplate configId="300404" autoFight="1" soundID="100103" preDesc="550404" />
<BattleConfigTemplate configId="300405" autoFight="1" soundID="100103" preDesc="550405" />
<BattleConfigTemplate configId="300406" autoFight="1" soundID="100103" preDesc="550406" />
<BattleConfigTemplate configId="300407" autoFight="1" soundID="100103" preDesc="550407" />
<BattleConfigTemplate configId="300408" autoFight="1" soundID="100103" preDesc="550408" />
<BattleConfigTemplate configId="300409" autoFight="1" soundID="100103" preDesc="550409" />
<BattleConfigTemplate configId="300410" autoFight="1" soundID="100103" preDesc="550410" />
<BattleConfigTemplate configId="300501" autoFight="1" soundID="100103" preDesc="550501" />
<BattleConfigTemplate configId="300502" autoFight="1" soundID="100103" preDesc="550502" />
<BattleConfigTemplate configId="300503" autoFight="1" soundID="100103" preDesc="550503" />
<BattleConfigTemplate configId="300504" autoFight="1" soundID="100103" preDesc="550504" />
<BattleConfigTemplate configId="300505" autoFight="1" soundID="100103" preDesc="550505" />
<BattleConfigTemplate configId="300506" autoFight="1" soundID="100103" preDesc="550506" />
<BattleConfigTemplate configId="300507" autoFight="1" soundID="100103" preDesc="550507" />
<BattleConfigTemplate configId="300508" autoFight="1" soundID="100103" preDesc="550508" />
<BattleConfigTemplate configId="300509" autoFight="1" soundID="100103" preDesc="550509" />
<BattleConfigTemplate configId="300510" autoFight="1" soundID="100103" preDesc="550510" />
</dataset>