<?xml version="1.0" encoding="UTF-8"?>
<dataset>
<BattleFlag flagId="1" forwardFlagId="1" triggerMode="0" x="15.24419" y="5.352532" z="-139.6815" rx="0" ry="351.9949" rz="0" cx="1" cy="1" cz="1" triggerCount="0" triggerFunc="4" willRelive="0" dieable="1" accountable="1" hideInDrama="0" hideWithDramable="0" guideId="0" hintLabelId="0" showOnUI="0" groupId="0" nodeSkill="0" alarmPosition="0,0,0" hoverPath="" triggerFlagEye2eye="0" triggerFlagEnter="1,2,3" triggerFlagAttack="0" triggerFlagKill="0" triggerFlagBlood="0" triggerFlagDistance="0" />
<BattleFlag flagId="2" forwardFlagId="1" triggerMode="0" x="13.41965" y="5.352532" z="-140.4229" rx="0" ry="351.9949" rz="0" cx="1" cy="1" cz="1" triggerCount="0" triggerFunc="4" willRelive="0" dieable="1" accountable="1" hideInDrama="0" hideWithDramable="0" guideId="0" hintLabelId="0" showOnUI="0" groupId="0" nodeSkill="0" alarmPosition="0,0,0" hoverPath="" triggerFlagEye2eye="0" triggerFlagEnter="1,2,3" triggerFlagAttack="0" triggerFlagKill="0" triggerFlagBlood="0" triggerFlagDistance="0" />
<BattleFlag flagId="3" forwardFlagId="1" triggerMode="0" x="17.2855" y="5.352532" z="-140.4645" rx="0" ry="351.9949" rz="0" cx="1" cy="1" cz="1" triggerCount="0" triggerFunc="4" willRelive="0" dieable="1" accountable="1" hideInDrama="0" hideWithDramable="0" guideId="0" hintLabelId="0" showOnUI="0" groupId="0" nodeSkill="0" alarmPosition="0,0,0" hoverPath="" triggerFlagEye2eye="0" triggerFlagEnter="1,2,3" triggerFlagAttack="0" triggerFlagKill="0" triggerFlagBlood="0" triggerFlagDistance="0" />
<BattleFlag flagId="101" forwardFlagId="1" triggerMode="0" x="17.94489" y="5.849041" z="-128.2238" rx="0" ry="351.9949" rz="0" cx="1" cy="1" cz="1" triggerCount="0" triggerFunc="4" willRelive="0" dieable="1" accountable="1" hideInDrama="0" hideWithDramable="0" guideId="0" hintLabelId="0" showOnUI="0" groupId="0" nodeSkill="0" alarmPosition="0,0,0" hoverPath="" triggerFlagEye2eye="101,102,103,104,105,106,107,108,109,110" triggerFlagEnter="101,102,103,104,105,106,107,108,109,110" triggerFlagAttack="0" triggerFlagKill="201,202,203,204,205,206,207,208,209,210" triggerFlagBlood="0" triggerFlagDistance="0" />
<BattleFlag flagId="102" forwardFlagId="1" triggerMode="0" x="20.00386" y="5.990557" z="-128.2877" rx="0" ry="351.9949" rz="0" cx="1" cy="1" cz="1" triggerCount="0" triggerFunc="4" willRelive="0" dieable="1" accountable="1" hideInDrama="0" hideWithDramable="0" guideId="0" hintLabelId="0" showOnUI="0" groupId="0" nodeSkill="0" alarmPosition="0,0,0" hoverPath="" triggerFlagEye2eye="101,102,103,104,105,106,107,108,109,110" triggerFlagEnter="101,102,103,104,105,106,107,108,109,110" triggerFlagAttack="0" triggerFlagKill="201,202,203,204,205,206,207,208,209,210" triggerFlagBlood="0" triggerFlagDistance="0" />
<BattleFlag flagId="103" forwardFlagId="1" triggerMode="0" x="21.94708" y="5.983821" z="-128.2467" rx="0" ry="351.9949" rz="0" cx="1" cy="1" cz="1" triggerCount="0" triggerFunc="4" willRelive="0" dieable="1" accountable="1" hideInDrama="0" hideWithDramable="0" guideId="0" hintLabelId="0" showOnUI="0" groupId="0" nodeSkill="0" alarmPosition="0,0,0" hoverPath="" triggerFlagEye2eye="101,102,103,104,105,106,107,108,109,110" triggerFlagEnter="101,102,103,104,105,106,107,108,109,110" triggerFlagAttack="0" triggerFlagKill="201,202,203,204,205,206,207,208,209,210" triggerFlagBlood="0" triggerFlagDistance="0" />
<BattleFlag flagId="104" forwardFlagId="1" triggerMode="0" x="23.8657" y="5.939398" z="-127.8153" rx="0" ry="351.9949" rz="0" cx="1" cy="1" cz="1" triggerCount="0" triggerFunc="4" willRelive="0" dieable="1" accountable="1" hideInDrama="0" hideWithDramable="0" guideId="0" hintLabelId="0" showOnUI="0" groupId="0" nodeSkill="0" alarmPosition="0,0,0" hoverPath="" triggerFlagEye2eye="101,102,103,104,105,106,107,108,109,110" triggerFlagEnter="101,102,103,104,105,106,107,108,109,110" triggerFlagAttack="0" triggerFlagKill="201,202,203,204,205,206,207,208,209,210" triggerFlagBlood="0" triggerFlagDistance="0" />
<BattleFlag flagId="105" forwardFlagId="1" triggerMode="0" x="17.90047" y="5.983821" z="-126.5436" rx="0" ry="351.9949" rz="0" cx="1" cy="1" cz="1" triggerCount="0" triggerFunc="4" willRelive="0" dieable="1" accountable="1" hideInDrama="0" hideWithDramable="0" guideId="0" hintLabelId="0" showOnUI="0" groupId="0" nodeSkill="0" alarmPosition="0,0,0" hoverPath="" triggerFlagEye2eye="101,102,103,104,105,106,107,108,109,110" triggerFlagEnter="101,102,103,104,105,106,107,108,109,110" triggerFlagAttack="0" triggerFlagKill="201,202,203,204,205,206,207,208,209,210" triggerFlagBlood="0" triggerFlagDistance="0" />
<BattleFlag flagId="106" forwardFlagId="1" triggerMode="0" x="19.64688" y="5.939398" z="-126.6111" rx="0" ry="351.9949" rz="0" cx="1" cy="1" cz="1" triggerCount="0" triggerFunc="4" willRelive="0" dieable="1" accountable="1" hideInDrama="0" hideWithDramable="0" guideId="0" hintLabelId="0" showOnUI="0" groupId="0" nodeSkill="0" alarmPosition="0,0,0" hoverPath="" triggerFlagEye2eye="101,102,103,104,105,106,107,108,109,110" triggerFlagEnter="101,102,103,104,105,106,107,108,109,110" triggerFlagAttack="0" triggerFlagKill="201,202,203,204,205,206,207,208,209,210" triggerFlagBlood="0" triggerFlagDistance="0" />
<BattleFlag flagId="107" forwardFlagId="1" triggerMode="0" x="21.44497" y="5.849041" z="-126.3279" rx="0" ry="351.9949" rz="0" cx="1" cy="1" cz="1" triggerCount="0" triggerFunc="4" willRelive="0" dieable="1" accountable="1" hideInDrama="0" hideWithDramable="0" guideId="0" hintLabelId="0" showOnUI="0" groupId="0" nodeSkill="0" alarmPosition="0,0,0" hoverPath="" triggerFlagEye2eye="101,102,103,104,105,106,107,108,109,110" triggerFlagEnter="101,102,103,104,105,106,107,108,109,110" triggerFlagAttack="0" triggerFlagKill="201,202,203,204,205,206,207,208,209,210" triggerFlagBlood="0" triggerFlagDistance="0" />
<BattleFlag flagId="108" forwardFlagId="1" triggerMode="0" x="23.23966" y="5.990557" z="-126.3078" rx="0" ry="351.9949" rz="0" cx="1" cy="1" cz="1" triggerCount="0" triggerFunc="4" willRelive="0" dieable="1" accountable="1" hideInDrama="0" hideWithDramable="0" guideId="0" hintLabelId="0" showOnUI="0" groupId="0" nodeSkill="0" alarmPosition="0,0,0" hoverPath="" triggerFlagEye2eye="101,102,103,104,105,106,107,108,109,110" triggerFlagEnter="101,102,103,104,105,106,107,108,109,110" triggerFlagAttack="0" triggerFlagKill="201,202,203,204,205,206,207,208,209,210" triggerFlagBlood="0" triggerFlagDistance="0" />
<BattleFlag flagId="109" forwardFlagId="1" triggerMode="0" x="18.44835" y="5.990557" z="-124.9821" rx="0" ry="351.9949" rz="0" cx="1" cy="1" cz="1" triggerCount="0" triggerFunc="4" willRelive="0" dieable="1" accountable="1" hideInDrama="0" hideWithDramable="0" guideId="0" hintLabelId="0" showOnUI="0" groupId="0" nodeSkill="0" alarmPosition="0,0,0" hoverPath="" triggerFlagEye2eye="101,102,103,104,105,106,107,108,109,110" triggerFlagEnter="101,102,103,104,105,106,107,108,109,110" triggerFlagAttack="0" triggerFlagKill="201,202,203,204,205,206,207,208,209,210" triggerFlagBlood="0" triggerFlagDistance="0" />
<BattleFlag flagId="110" forwardFlagId="1" triggerMode="0" x="20.97629" y="5.849041" z="-124.6468" rx="0" ry="351.9949" rz="0" cx="1" cy="1" cz="1" triggerCount="0" triggerFunc="4" willRelive="0" dieable="1" accountable="1" hideInDrama="0" hideWithDramable="0" guideId="0" hintLabelId="0" showOnUI="0" groupId="0" nodeSkill="0" alarmPosition="0,0,0" hoverPath="" triggerFlagEye2eye="101,102,103,104,105,106,107,108,109,110" triggerFlagEnter="101,102,103,104,105,106,107,108,109,110" triggerFlagAttack="0" triggerFlagKill="201,202,203,204,205,206,207,208,209,210" triggerFlagBlood="0" triggerFlagDistance="0" />
<BattleFlag flagId="201" forwardFlagId="1" triggerMode="0" x="18.2933" y="5.496498" z="-122.8025" rx="0" ry="340.2843" rz="0" cx="1" cy="1" cz="1" triggerCount="10" triggerFunc="2" willRelive="0" dieable="1" accountable="1" hideInDrama="0" hideWithDramable="0" guideId="0" hintLabelId="0" showOnUI="0" groupId="0" nodeSkill="0" alarmPosition="0,0,0" hoverPath="" triggerFlagEye2eye="201,202,203,204,205,206,207,208,209,210" triggerFlagEnter="201,202,203,204,205,206,207,208,209,210" triggerFlagAttack="0" triggerFlagKill="1001,310,309,308,307,306,305,304,303,302,301" triggerFlagBlood="0" triggerFlagDistance="0" />
<BattleFlag flagId="202" forwardFlagId="1" triggerMode="0" x="20.23359" y="5.481409" z="-123.4586" rx="0" ry="340.2843" rz="0" cx="1" cy="1" cz="1" triggerCount="10" triggerFunc="2" willRelive="0" dieable="1" accountable="1" hideInDrama="0" hideWithDramable="0" guideId="0" hintLabelId="0" showOnUI="0" groupId="0" nodeSkill="0" alarmPosition="0,0,0" hoverPath="" triggerFlagEye2eye="201,202,203,204,205,206,207,208,209,210" triggerFlagEnter="201,202,203,204,205,206,207,208,209,210" triggerFlagAttack="0" triggerFlagKill="1001,310,309,308,307,306,305,304,303,302,301" triggerFlagBlood="0" triggerFlagDistance="0" />
<BattleFlag flagId="203" forwardFlagId="1" triggerMode="0" x="22.2466" y="5.43617" z="-123.842" rx="0" ry="340.2843" rz="0" cx="1" cy="1" cz="1" triggerCount="10" triggerFunc="2" willRelive="0" dieable="1" accountable="1" hideInDrama="0" hideWithDramable="0" guideId="0" hintLabelId="0" showOnUI="0" groupId="0" nodeSkill="0" alarmPosition="0,0,0" hoverPath="" triggerFlagEye2eye="201,202,203,204,205,206,207,208,209,210" triggerFlagEnter="201,202,203,204,205,206,207,208,209,210" triggerFlagAttack="0" triggerFlagKill="1001,310,309,308,307,306,305,304,303,302,301" triggerFlagBlood="0" triggerFlagDistance="0" />
<BattleFlag flagId="204" forwardFlagId="1" triggerMode="0" x="24.3984" y="5.43617" z="-124.1352" rx="0" ry="340.2843" rz="0" cx="1" cy="1" cz="1" triggerCount="10" triggerFunc="2" willRelive="0" dieable="1" accountable="1" hideInDrama="0" hideWithDramable="0" guideId="0" hintLabelId="0" showOnUI="0" groupId="0" nodeSkill="0" alarmPosition="0,0,0" hoverPath="" triggerFlagEye2eye="201,202,203,204,205,206,207,208,209,210" triggerFlagEnter="201,202,203,204,205,206,207,208,209,210" triggerFlagAttack="0" triggerFlagKill="1001,310,309,308,307,306,305,304,303,302,301" triggerFlagBlood="0" triggerFlagDistance="0" />
<BattleFlag flagId="205" forwardFlagId="1" triggerMode="0" x="18.85758" y="5.481409" z="-120.8549" rx="0" ry="340.2843" rz="0" cx="1" cy="1" cz="1" triggerCount="10" triggerFunc="2" willRelive="0" dieable="1" accountable="1" hideInDrama="0" hideWithDramable="0" guideId="0" hintLabelId="0" showOnUI="0" groupId="0" nodeSkill="0" alarmPosition="0,0,0" hoverPath="" triggerFlagEye2eye="201,202,203,204,205,206,207,208,209,210" triggerFlagEnter="201,202,203,204,205,206,207,208,209,210" triggerFlagAttack="0" triggerFlagKill="1001,310,309,308,307,306,305,304,303,302,301" triggerFlagBlood="0" triggerFlagDistance="0" />
<BattleFlag flagId="206" forwardFlagId="1" triggerMode="0" x="20.78486" y="5.354865" z="-119.6952" rx="0" ry="340.2843" rz="0" cx="1" cy="1" cz="1" triggerCount="10" triggerFunc="2" willRelive="0" dieable="1" accountable="1" hideInDrama="0" hideWithDramable="0" guideId="0" hintLabelId="0" showOnUI="0" groupId="0" nodeSkill="0" alarmPosition="0,0,0" hoverPath="" triggerFlagEye2eye="201,202,203,204,205,206,207,208,209,210" triggerFlagEnter="201,202,203,204,205,206,207,208,209,210" triggerFlagAttack="0" triggerFlagKill="1001,310,309,308,307,306,305,304,303,302,301" triggerFlagBlood="0" triggerFlagDistance="0" />
<BattleFlag flagId="207" forwardFlagId="1" triggerMode="0" x="23.18113" y="5.43617" z="-120.0752" rx="0" ry="340.2843" rz="0" cx="1" cy="1" cz="1" triggerCount="10" triggerFunc="2" willRelive="0" dieable="1" accountable="1" hideInDrama="0" hideWithDramable="0" guideId="0" hintLabelId="0" showOnUI="0" groupId="0" nodeSkill="0" alarmPosition="0,0,0" hoverPath="" triggerFlagEye2eye="201,202,203,204,205,206,207,208,209,210" triggerFlagEnter="201,202,203,204,205,206,207,208,209,210" triggerFlagAttack="0" triggerFlagKill="1001,310,309,308,307,306,305,304,303,302,301" triggerFlagBlood="0" triggerFlagDistance="0" />
<BattleFlag flagId="208" forwardFlagId="1" triggerMode="0" x="24.36899" y="5.481409" z="-122.0591" rx="0" ry="340.2843" rz="0" cx="1" cy="1" cz="1" triggerCount="10" triggerFunc="2" willRelive="0" dieable="1" accountable="1" hideInDrama="0" hideWithDramable="0" guideId="0" hintLabelId="0" showOnUI="0" groupId="0" nodeSkill="0" alarmPosition="0,0,0" hoverPath="" triggerFlagEye2eye="201,202,203,204,205,206,207,208,209,210" triggerFlagEnter="201,202,203,204,205,206,207,208,209,210" triggerFlagAttack="0" triggerFlagKill="1001,310,309,308,307,306,305,304,303,302,301" triggerFlagBlood="0" triggerFlagDistance="0" />
<BattleFlag flagId="209" forwardFlagId="1" triggerMode="0" x="21.59874" y="5.496498" z="-121.964" rx="0" ry="340.2843" rz="0" cx="1" cy="1" cz="1" triggerCount="10" triggerFunc="2" willRelive="0" dieable="1" accountable="1" hideInDrama="0" hideWithDramable="0" guideId="0" hintLabelId="0" showOnUI="0" groupId="0" nodeSkill="0" alarmPosition="0,0,0" hoverPath="" triggerFlagEye2eye="201,202,203,204,205,206,207,208,209,210" triggerFlagEnter="201,202,203,204,205,206,207,208,209,210" triggerFlagAttack="0" triggerFlagKill="1001,310,309,308,307,306,305,304,303,302,301" triggerFlagBlood="0" triggerFlagDistance="0" />
<BattleFlag flagId="210" forwardFlagId="1" triggerMode="0" x="25.66297" y="5.404366" z="-120.7764" rx="0" ry="340.2843" rz="0" cx="1" cy="1" cz="1" triggerCount="10" triggerFunc="2" willRelive="0" dieable="1" accountable="1" hideInDrama="0" hideWithDramable="0" guideId="0" hintLabelId="0" showOnUI="0" groupId="0" nodeSkill="0" alarmPosition="0,0,0" hoverPath="" triggerFlagEye2eye="201,202,203,204,205,206,207,208,209,210" triggerFlagEnter="201,202,203,204,205,206,207,208,209,210" triggerFlagAttack="0" triggerFlagKill="1001,310,309,308,307,306,305,304,303,302,301" triggerFlagBlood="0" triggerFlagDistance="0" />
<BattleFlag flagId="310" forwardFlagId="1" triggerMode="0" x="26.88246" y="5.979383" z="-110.2035" rx="0" ry="351.9949" rz="0" cx="1" cy="1" cz="1" triggerCount="10" triggerFunc="2" willRelive="0" dieable="1" accountable="1" hideInDrama="0" hideWithDramable="0" guideId="0" hintLabelId="0" showOnUI="0" groupId="0" nodeSkill="0" alarmPosition="0,0,0" hoverPath="" triggerFlagEye2eye="310,309,308,307,306,305,304,303,302,301" triggerFlagEnter="310,309,308,307,306,305,304,303,302,301" triggerFlagAttack="0" triggerFlagKill="401,402,403,404,405,406,407,408,409,410" triggerFlagBlood="0" triggerFlagDistance="0" />
<BattleFlag flagId="309" forwardFlagId="1" triggerMode="0" x="24.70034" y="5.979383" z="-109.5511" rx="0" ry="351.9949" rz="0" cx="1" cy="1" cz="1" triggerCount="10" triggerFunc="2" willRelive="0" dieable="1" accountable="1" hideInDrama="0" hideWithDramable="0" guideId="0" hintLabelId="0" showOnUI="0" groupId="0" nodeSkill="0" alarmPosition="0,0,0" hoverPath="" triggerFlagEye2eye="310,309,308,307,306,305,304,303,302,301" triggerFlagEnter="310,309,308,307,306,305,304,303,302,301" triggerFlagAttack="0" triggerFlagKill="401,402,403,404,405,406,407,408,409,410" triggerFlagBlood="0" triggerFlagDistance="0" />
<BattleFlag flagId="308" forwardFlagId="1" triggerMode="0" x="23.18817" y="5.384993" z="-108.4206" rx="0" ry="351.9949" rz="0" cx="1" cy="1" cz="1" triggerCount="10" triggerFunc="2" willRelive="0" dieable="1" accountable="1" hideInDrama="0" hideWithDramable="0" guideId="0" hintLabelId="0" showOnUI="0" groupId="0" nodeSkill="0" alarmPosition="0,0,0" hoverPath="" triggerFlagEye2eye="310,309,308,307,306,305,304,303,302,301" triggerFlagEnter="310,309,308,307,306,305,304,303,302,301" triggerFlagAttack="0" triggerFlagKill="401,402,403,404,405,406,407,408,409,410" triggerFlagBlood="0" triggerFlagDistance="0" />
<BattleFlag flagId="307" forwardFlagId="1" triggerMode="0" x="21.26212" y="5.919054" z="-108.3684" rx="0" ry="351.9949" rz="0" cx="1" cy="1" cz="1" triggerCount="10" triggerFunc="2" willRelive="0" dieable="1" accountable="1" hideInDrama="0" hideWithDramable="0" guideId="0" hintLabelId="0" showOnUI="0" groupId="0" nodeSkill="0" alarmPosition="0,0,0" hoverPath="" triggerFlagEye2eye="310,309,308,307,306,305,304,303,302,301" triggerFlagEnter="310,309,308,307,306,305,304,303,302,301" triggerFlagAttack="0" triggerFlagKill="401,402,403,404,405,406,407,408,409,410" triggerFlagBlood="0" triggerFlagDistance="0" />
<BattleFlag flagId="306" forwardFlagId="1" triggerMode="0" x="19.57605" y="5.979383" z="-107.8683" rx="0" ry="351.9949" rz="0" cx="1" cy="1" cz="1" triggerCount="10" triggerFunc="2" willRelive="0" dieable="1" accountable="1" hideInDrama="0" hideWithDramable="0" guideId="0" hintLabelId="0" showOnUI="0" groupId="0" nodeSkill="0" alarmPosition="0,0,0" hoverPath="" triggerFlagEye2eye="310,309,308,307,306,305,304,303,302,301" triggerFlagEnter="310,309,308,307,306,305,304,303,302,301" triggerFlagAttack="0" triggerFlagKill="401,402,403,404,405,406,407,408,409,410" triggerFlagBlood="0" triggerFlagDistance="0" />
<BattleFlag flagId="305" forwardFlagId="1" triggerMode="0" x="22.67295" y="5.964293" z="-111.2197" rx="0" ry="351.9949" rz="0" cx="1" cy="1" cz="1" triggerCount="10" triggerFunc="2" willRelive="0" dieable="1" accountable="1" hideInDrama="0" hideWithDramable="0" guideId="0" hintLabelId="0" showOnUI="0" groupId="0" nodeSkill="0" alarmPosition="0,0,0" hoverPath="" triggerFlagEye2eye="310,309,308,307,306,305,304,303,302,301" triggerFlagEnter="310,309,308,307,306,305,304,303,302,301" triggerFlagAttack="0" triggerFlagKill="401,402,403,404,405,406,407,408,409,410" triggerFlagBlood="0" triggerFlagDistance="0" />
<BattleFlag flagId="304" forwardFlagId="1" triggerMode="0" x="25.26079" y="5.919054" z="-114.5416" rx="0" ry="351.9949" rz="0" cx="1" cy="1" cz="1" triggerCount="10" triggerFunc="2" willRelive="0" dieable="1" accountable="1" hideInDrama="0" hideWithDramable="0" guideId="0" hintLabelId="0" showOnUI="0" groupId="0" nodeSkill="0" alarmPosition="0,0,0" hoverPath="" triggerFlagEye2eye="310,309,308,307,306,305,304,303,302,301" triggerFlagEnter="310,309,308,307,306,305,304,303,302,301" triggerFlagAttack="0" triggerFlagKill="401,402,403,404,405,406,407,408,409,410" triggerFlagBlood="0" triggerFlagDistance="0" />
<BattleFlag flagId="303" forwardFlagId="1" triggerMode="0" x="18.65313" y="5.919054" z="-112.1485" rx="0" ry="351.9949" rz="0" cx="1" cy="1" cz="1" triggerCount="10" triggerFunc="2" willRelive="0" dieable="1" accountable="1" hideInDrama="0" hideWithDramable="0" guideId="0" hintLabelId="0" showOnUI="0" groupId="0" nodeSkill="0" alarmPosition="0,0,0" hoverPath="" triggerFlagEye2eye="310,309,308,307,306,305,304,303,302,301" triggerFlagEnter="310,309,308,307,306,305,304,303,302,301" triggerFlagAttack="0" triggerFlagKill="401,402,403,404,405,406,407,408,409,410" triggerFlagBlood="0" triggerFlagDistance="0" />
<BattleFlag flagId="302" forwardFlagId="1" triggerMode="0" x="22.82893" y="5.964293" z="-113.6214" rx="0" ry="351.9949" rz="0" cx="1" cy="1" cz="1" triggerCount="10" triggerFunc="2" willRelive="0" dieable="1" accountable="1" hideInDrama="0" hideWithDramable="0" guideId="0" hintLabelId="0" showOnUI="0" groupId="0" nodeSkill="0" alarmPosition="0,0,0" hoverPath="" triggerFlagEye2eye="310,309,308,307,306,305,304,303,302,301" triggerFlagEnter="310,309,308,307,306,305,304,303,302,301" triggerFlagAttack="0" triggerFlagKill="401,402,403,404,405,406,407,408,409,410" triggerFlagBlood="0" triggerFlagDistance="0" />
<BattleFlag flagId="301" forwardFlagId="1" triggerMode="0" x="20.82907" y="5.979383" z="-113.0442" rx="0" ry="351.9949" rz="0" cx="1" cy="1" cz="1" triggerCount="10" triggerFunc="2" willRelive="0" dieable="1" accountable="1" hideInDrama="0" hideWithDramable="0" guideId="0" hintLabelId="0" showOnUI="0" groupId="0" nodeSkill="0" alarmPosition="0,0,0" hoverPath="" triggerFlagEye2eye="310,309,308,307,306,305,304,303,302,301" triggerFlagEnter="310,309,308,307,306,305,304,303,302,301" triggerFlagAttack="0" triggerFlagKill="401,402,403,404,405,406,407,408,409,410" triggerFlagBlood="0" triggerFlagDistance="0" />
<BattleFlag flagId="401" forwardFlagId="1" triggerMode="0" x="19.14138" y="5.979383" z="-100.9716" rx="0" ry="351.9949" rz="0" cx="1" cy="1" cz="1" triggerCount="10" triggerFunc="2" willRelive="0" dieable="1" accountable="1" hideInDrama="0" hideWithDramable="0" guideId="0" hintLabelId="0" showOnUI="0" groupId="0" nodeSkill="0" alarmPosition="0,0,0" hoverPath="" triggerFlagEye2eye="401,402,403,404,405,406,407,408,409,410" triggerFlagEnter="401,402,403,404,405,406,407,408,409,410" triggerFlagAttack="0" triggerFlagKill="501,502,503,504,505,506,507,508,509,510" triggerFlagBlood="0" triggerFlagDistance="0" />
<BattleFlag flagId="402" forwardFlagId="1" triggerMode="0" x="21.04375" y="5.964293" z="-100.8556" rx="0" ry="351.9949" rz="0" cx="1" cy="1" cz="1" triggerCount="10" triggerFunc="2" willRelive="0" dieable="1" accountable="1" hideInDrama="0" hideWithDramable="0" guideId="0" hintLabelId="0" showOnUI="0" groupId="0" nodeSkill="0" alarmPosition="0,0,0" hoverPath="" triggerFlagEye2eye="401,402,403,404,405,406,407,408,409,410" triggerFlagEnter="401,402,403,404,405,406,407,408,409,410" triggerFlagAttack="0" triggerFlagKill="501,502,503,504,505,506,507,508,509,510" triggerFlagBlood="0" triggerFlagDistance="0" />
<BattleFlag flagId="403" forwardFlagId="1" triggerMode="0" x="23.38509" y="5.919055" z="-101.1322" rx="0" ry="351.9949" rz="0" cx="1" cy="1" cz="1" triggerCount="10" triggerFunc="2" willRelive="0" dieable="1" accountable="1" hideInDrama="0" hideWithDramable="0" guideId="0" hintLabelId="0" showOnUI="0" groupId="0" nodeSkill="0" alarmPosition="0,0,0" hoverPath="" triggerFlagEye2eye="401,402,403,404,405,406,407,408,409,410" triggerFlagEnter="401,402,403,404,405,406,407,408,409,410" triggerFlagAttack="0" triggerFlagKill="501,502,503,504,505,506,507,508,509,510" triggerFlagBlood="0" triggerFlagDistance="0" />
<BattleFlag flagId="404" forwardFlagId="1" triggerMode="0" x="25.37613" y="5.919055" z="-101.2157" rx="0" ry="351.9949" rz="0" cx="1" cy="1" cz="1" triggerCount="10" triggerFunc="2" willRelive="0" dieable="1" accountable="1" hideInDrama="0" hideWithDramable="0" guideId="0" hintLabelId="0" showOnUI="0" groupId="0" nodeSkill="0" alarmPosition="0,0,0" hoverPath="" triggerFlagEye2eye="401,402,403,404,405,406,407,408,409,410" triggerFlagEnter="401,402,403,404,405,406,407,408,409,410" triggerFlagAttack="0" triggerFlagKill="501,502,503,504,505,506,507,508,509,510" triggerFlagBlood="0" triggerFlagDistance="0" />
<BattleFlag flagId="405" forwardFlagId="1" triggerMode="0" x="27.81835" y="5.964293" z="-101.9225" rx="0" ry="351.9949" rz="0" cx="1" cy="1" cz="1" triggerCount="10" triggerFunc="2" willRelive="0" dieable="1" accountable="1" hideInDrama="0" hideWithDramable="0" guideId="0" hintLabelId="0" showOnUI="0" groupId="0" nodeSkill="0" alarmPosition="0,0,0" hoverPath="" triggerFlagEye2eye="401,402,403,404,405,406,407,408,409,410" triggerFlagEnter="401,402,403,404,405,406,407,408,409,410" triggerFlagAttack="0" triggerFlagKill="501,502,503,504,505,506,507,508,509,510" triggerFlagBlood="0" triggerFlagDistance="0" />
<BattleFlag flagId="406" forwardFlagId="1" triggerMode="0" x="19.91005" y="5.979383" z="-98.68226" rx="0" ry="351.9949" rz="0" cx="1" cy="1" cz="1" triggerCount="10" triggerFunc="2" willRelive="0" dieable="1" accountable="1" hideInDrama="0" hideWithDramable="0" guideId="0" hintLabelId="0" showOnUI="0" groupId="0" nodeSkill="0" alarmPosition="0,0,0" hoverPath="" triggerFlagEye2eye="401,402,403,404,405,406,407,408,409,410" triggerFlagEnter="401,402,403,404,405,406,407,408,409,410" triggerFlagAttack="0" triggerFlagKill="501,502,503,504,505,506,507,508,509,510" triggerFlagBlood="0" triggerFlagDistance="0" />
<BattleFlag flagId="407" forwardFlagId="1" triggerMode="0" x="21.82187" y="5.919055" z="-98.77694" rx="0" ry="351.9949" rz="0" cx="1" cy="1" cz="1" triggerCount="10" triggerFunc="2" willRelive="0" dieable="1" accountable="1" hideInDrama="0" hideWithDramable="0" guideId="0" hintLabelId="0" showOnUI="0" groupId="0" nodeSkill="0" alarmPosition="0,0,0" hoverPath="" triggerFlagEye2eye="401,402,403,404,405,406,407,408,409,410" triggerFlagEnter="401,402,403,404,405,406,407,408,409,410" triggerFlagAttack="0" triggerFlagKill="501,502,503,504,505,506,507,508,509,510" triggerFlagBlood="0" triggerFlagDistance="0" />
<BattleFlag flagId="408" forwardFlagId="1" triggerMode="0" x="23.97862" y="5.964293" z="-99.39259" rx="0" ry="351.9949" rz="0" cx="1" cy="1" cz="1" triggerCount="10" triggerFunc="2" willRelive="0" dieable="1" accountable="1" hideInDrama="0" hideWithDramable="0" guideId="0" hintLabelId="0" showOnUI="0" groupId="0" nodeSkill="0" alarmPosition="0,0,0" hoverPath="" triggerFlagEye2eye="401,402,403,404,405,406,407,408,409,410" triggerFlagEnter="401,402,403,404,405,406,407,408,409,410" triggerFlagAttack="0" triggerFlagKill="501,502,503,504,505,506,507,508,509,510" triggerFlagBlood="0" triggerFlagDistance="0" />
<BattleFlag flagId="409" forwardFlagId="1" triggerMode="0" x="26.39299" y="5.979383" z="-99.90131" rx="0" ry="351.9949" rz="0" cx="1" cy="1" cz="1" triggerCount="10" triggerFunc="2" willRelive="0" dieable="1" accountable="1" hideInDrama="0" hideWithDramable="0" guideId="0" hintLabelId="0" showOnUI="0" groupId="0" nodeSkill="0" alarmPosition="0,0,0" hoverPath="" triggerFlagEye2eye="401,402,403,404,405,406,407,408,409,410" triggerFlagEnter="401,402,403,404,405,406,407,408,409,410" triggerFlagAttack="0" triggerFlagKill="501,502,503,504,505,506,507,508,509,510" triggerFlagBlood="0" triggerFlagDistance="0" />
<BattleFlag flagId="410" forwardFlagId="1" triggerMode="0" x="22.92676" y="5.979383" z="-96.65237" rx="0" ry="351.9949" rz="0" cx="1" cy="1" cz="1" triggerCount="10" triggerFunc="2" willRelive="0" dieable="1" accountable="1" hideInDrama="0" hideWithDramable="0" guideId="0" hintLabelId="0" showOnUI="0" groupId="0" nodeSkill="0" alarmPosition="0,0,0" hoverPath="" triggerFlagEye2eye="401,402,403,404,405,406,407,408,409,410" triggerFlagEnter="401,402,403,404,405,406,407,408,409,410" triggerFlagAttack="0" triggerFlagKill="501,502,503,504,505,506,507,508,509,510" triggerFlagBlood="0" triggerFlagDistance="0" />
<BattleFlag flagId="501" forwardFlagId="1" triggerMode="0" x="20.27837" y="5.36414" z="-85.43185" rx="0" ry="351.9949" rz="0" cx="1" cy="1" cz="1" triggerCount="10" triggerFunc="2" willRelive="0" dieable="1" accountable="1" hideInDrama="0" hideWithDramable="0" guideId="0" hintLabelId="0" showOnUI="0" groupId="0" nodeSkill="0" alarmPosition="0,0,0" hoverPath="" triggerFlagEye2eye="501,502,503,504,505,506,507,508,509,510" triggerFlagEnter="501,502,503,504,505,506,507,508,509,510" triggerFlagAttack="0" triggerFlagKill="2001,2002,601,602,603,604,605,606,607,608,609,610" triggerFlagBlood="0" triggerFlagDistance="0" />
<BattleFlag flagId="502" forwardFlagId="1" triggerMode="0" x="22.79268" y="5.505655" z="-83.56351" rx="0" ry="351.9949" rz="0" cx="1" cy="1" cz="1" triggerCount="10" triggerFunc="2" willRelive="0" dieable="1" accountable="1" hideInDrama="0" hideWithDramable="0" guideId="0" hintLabelId="0" showOnUI="0" groupId="0" nodeSkill="0" alarmPosition="0,0,0" hoverPath="" triggerFlagEye2eye="501,502,503,504,505,506,507,508,509,510" triggerFlagEnter="501,502,503,504,505,506,507,508,509,510" triggerFlagAttack="0" triggerFlagKill="2001,2002,601,602,603,604,605,606,607,608,609,610" triggerFlagBlood="0" triggerFlagDistance="0" />
<BattleFlag flagId="503" forwardFlagId="1" triggerMode="0" x="25.09704" y="5.329705" z="-83.28993" rx="0" ry="351.9949" rz="0" cx="1" cy="1" cz="1" triggerCount="10" triggerFunc="2" willRelive="0" dieable="1" accountable="1" hideInDrama="0" hideWithDramable="0" guideId="0" hintLabelId="0" showOnUI="0" groupId="0" nodeSkill="0" alarmPosition="0,0,0" hoverPath="" triggerFlagEye2eye="501,502,503,504,505,506,507,508,509,510" triggerFlagEnter="501,502,503,504,505,506,507,508,509,510" triggerFlagAttack="0" triggerFlagKill="2001,2002,601,602,603,604,605,606,607,608,609,610" triggerFlagBlood="0" triggerFlagDistance="0" />
<BattleFlag flagId="504" forwardFlagId="1" triggerMode="0" x="27.92764" y="5.498919" z="-84.89134" rx="0" ry="351.9949" rz="0" cx="1" cy="1" cz="1" triggerCount="10" triggerFunc="2" willRelive="0" dieable="1" accountable="1" hideInDrama="0" hideWithDramable="0" guideId="0" hintLabelId="0" showOnUI="0" groupId="0" nodeSkill="0" alarmPosition="0,0,0" hoverPath="" triggerFlagEye2eye="501,502,503,504,505,506,507,508,509,510" triggerFlagEnter="501,502,503,504,505,506,507,508,509,510" triggerFlagAttack="0" triggerFlagKill="2001,2002,601,602,603,604,605,606,607,608,609,610" triggerFlagBlood="0" triggerFlagDistance="0" />
<BattleFlag flagId="505" forwardFlagId="1" triggerMode="0" x="20.2799" y="5.498919" z="-82.78586" rx="0" ry="351.9949" rz="0" cx="1" cy="1" cz="1" triggerCount="10" triggerFunc="2" willRelive="0" dieable="1" accountable="1" hideInDrama="0" hideWithDramable="0" guideId="0" hintLabelId="0" showOnUI="0" groupId="0" nodeSkill="0" alarmPosition="0,0,0" hoverPath="" triggerFlagEye2eye="501,502,503,504,505,506,507,508,509,510" triggerFlagEnter="501,502,503,504,505,506,507,508,509,510" triggerFlagAttack="0" triggerFlagKill="2001,2002,601,602,603,604,605,606,607,608,609,610" triggerFlagBlood="0" triggerFlagDistance="0" />
<BattleFlag flagId="506" forwardFlagId="1" triggerMode="0" x="27.03917" y="5.36414" z="-81.805" rx="0" ry="351.9949" rz="0" cx="1" cy="1" cz="1" triggerCount="10" triggerFunc="2" willRelive="0" dieable="1" accountable="1" hideInDrama="0" hideWithDramable="0" guideId="0" hintLabelId="0" showOnUI="0" groupId="0" nodeSkill="0" alarmPosition="0,0,0" hoverPath="" triggerFlagEye2eye="501,502,503,504,505,506,507,508,509,510" triggerFlagEnter="501,502,503,504,505,506,507,508,509,510" triggerFlagAttack="0" triggerFlagKill="2001,2002,601,602,603,604,605,606,607,608,609,610" triggerFlagBlood="0" triggerFlagDistance="0" />
<BattleFlag flagId="507" forwardFlagId="1" triggerMode="0" x="23.65961" y="5.465127" z="-80.96748" rx="0" ry="351.9949" rz="0" cx="1" cy="1" cz="1" triggerCount="10" triggerFunc="2" willRelive="0" dieable="1" accountable="1" hideInDrama="0" hideWithDramable="0" guideId="0" hintLabelId="0" showOnUI="0" groupId="0" nodeSkill="0" alarmPosition="0,0,0" hoverPath="" triggerFlagEye2eye="501,502,503,504,505,506,507,508,509,510" triggerFlagEnter="501,502,503,504,505,506,507,508,509,510" triggerFlagAttack="0" triggerFlagKill="2001,2002,601,602,603,604,605,606,607,608,609,610" triggerFlagBlood="0" triggerFlagDistance="0" />
<BattleFlag flagId="508" forwardFlagId="1" triggerMode="0" x="17.94051" y="5.231309" z="-81.31734" rx="0" ry="351.9949" rz="0" cx="1" cy="1" cz="1" triggerCount="10" triggerFunc="2" willRelive="0" dieable="1" accountable="1" hideInDrama="0" hideWithDramable="0" guideId="0" hintLabelId="0" showOnUI="0" groupId="0" nodeSkill="0" alarmPosition="0,0,0" hoverPath="" triggerFlagEye2eye="501,502,503,504,505,506,507,508,509,510" triggerFlagEnter="501,502,503,504,505,506,507,508,509,510" triggerFlagAttack="0" triggerFlagKill="2001,2002,601,602,603,604,605,606,607,608,609,610" triggerFlagBlood="0" triggerFlagDistance="0" />
<BattleFlag flagId="509" forwardFlagId="1" triggerMode="0" x="28.24635" y="5.355221" z="-80.12047" rx="0" ry="351.9949" rz="0" cx="1" cy="1" cz="1" triggerCount="10" triggerFunc="2" willRelive="0" dieable="1" accountable="1" hideInDrama="0" hideWithDramable="0" guideId="0" hintLabelId="0" showOnUI="0" groupId="0" nodeSkill="0" alarmPosition="0,0,0" hoverPath="" triggerFlagEye2eye="501,502,503,504,505,506,507,508,509,510" triggerFlagEnter="501,502,503,504,505,506,507,508,509,510" triggerFlagAttack="0" triggerFlagKill="2001,2002,601,602,603,604,605,606,607,608,609,610" triggerFlagBlood="0" triggerFlagDistance="0" />
<BattleFlag flagId="510" forwardFlagId="1" triggerMode="0" x="24.14068" y="5.439741" z="-85.39362" rx="0" ry="351.9949" rz="0" cx="1" cy="1" cz="1" triggerCount="10" triggerFunc="2" willRelive="0" dieable="1" accountable="1" hideInDrama="0" hideWithDramable="0" guideId="0" hintLabelId="0" showOnUI="0" groupId="0" nodeSkill="0" alarmPosition="0,0,0" hoverPath="" triggerFlagEye2eye="501,502,503,504,505,506,507,508,509,510" triggerFlagEnter="501,502,503,504,505,506,507,508,509,510" triggerFlagAttack="0" triggerFlagKill="2001,2002,601,602,603,604,605,606,607,608,609,610" triggerFlagBlood="0" triggerFlagDistance="0" />
<BattleFlag flagId="601" forwardFlagId="1" triggerMode="0" x="49.79752" y="5.979382" z="-89.49509" rx="0" ry="351.9949" rz="0" cx="1" cy="1" cz="1" triggerCount="10" triggerFunc="2" willRelive="0" dieable="1" accountable="1" hideInDrama="0" hideWithDramable="0" guideId="0" hintLabelId="0" showOnUI="0" groupId="0" nodeSkill="0" alarmPosition="0,0,0" hoverPath="" triggerFlagEye2eye="601,602,603,604,605,606,607,608,609,610" triggerFlagEnter="0" triggerFlagAttack="0" triggerFlagKill="0" triggerFlagBlood="0" triggerFlagDistance="0" />
<BattleFlag flagId="602" forwardFlagId="1" triggerMode="0" x="53.35813" y="5.964293" z="-87.06334" rx="0" ry="351.9949" rz="0" cx="1" cy="1" cz="1" triggerCount="10" triggerFunc="2" willRelive="0" dieable="1" accountable="1" hideInDrama="0" hideWithDramable="0" guideId="0" hintLabelId="0" showOnUI="0" groupId="0" nodeSkill="0" alarmPosition="0,0,0" hoverPath="" triggerFlagEye2eye="601,602,603,604,605,606,607,608,609,610" triggerFlagEnter="0" triggerFlagAttack="0" triggerFlagKill="0" triggerFlagBlood="0" triggerFlagDistance="0" />
<BattleFlag flagId="603" forwardFlagId="1" triggerMode="0" x="52.80299" y="5.919054" z="-91.21937" rx="0" ry="351.9949" rz="0" cx="1" cy="1" cz="1" triggerCount="10" triggerFunc="2" willRelive="0" dieable="1" accountable="1" hideInDrama="0" hideWithDramable="0" guideId="0" hintLabelId="0" showOnUI="0" groupId="0" nodeSkill="0" alarmPosition="0,0,0" hoverPath="" triggerFlagEye2eye="601,602,603,604,605,606,607,608,609,610" triggerFlagEnter="0" triggerFlagAttack="0" triggerFlagKill="0" triggerFlagBlood="0" triggerFlagDistance="0" />
<BattleFlag flagId="604" forwardFlagId="1" triggerMode="0" x="50.31063" y="5.919054" z="-95.59247" rx="0" ry="351.9949" rz="0" cx="1" cy="1" cz="1" triggerCount="10" triggerFunc="2" willRelive="0" dieable="1" accountable="1" hideInDrama="0" hideWithDramable="0" guideId="0" hintLabelId="0" showOnUI="0" groupId="0" nodeSkill="0" alarmPosition="0,0,0" hoverPath="" triggerFlagEye2eye="601,602,603,604,605,606,607,608,609,610" triggerFlagEnter="0" triggerFlagAttack="0" triggerFlagKill="0" triggerFlagBlood="0" triggerFlagDistance="0" />
<BattleFlag flagId="605" forwardFlagId="1" triggerMode="0" x="48.48158" y="5.964293" z="-93.03371" rx="0" ry="351.9949" rz="0" cx="1" cy="1" cz="1" triggerCount="10" triggerFunc="2" willRelive="0" dieable="1" accountable="1" hideInDrama="0" hideWithDramable="0" guideId="0" hintLabelId="0" showOnUI="0" groupId="0" nodeSkill="0" alarmPosition="0,0,0" hoverPath="" triggerFlagEye2eye="601,602,603,604,605,606,607,608,609,610" triggerFlagEnter="0" triggerFlagAttack="0" triggerFlagKill="0" triggerFlagBlood="0" triggerFlagDistance="0" />
<BattleFlag flagId="606" forwardFlagId="1" triggerMode="0" x="45.07797" y="5.979382" z="-92.06586" rx="0" ry="351.9949" rz="0" cx="1" cy="1" cz="1" triggerCount="10" triggerFunc="2" willRelive="0" dieable="1" accountable="1" hideInDrama="0" hideWithDramable="0" guideId="0" hintLabelId="0" showOnUI="0" groupId="0" nodeSkill="0" alarmPosition="0,0,0" hoverPath="" triggerFlagEye2eye="601,602,603,604,605,606,607,608,609,610" triggerFlagEnter="0" triggerFlagAttack="0" triggerFlagKill="0" triggerFlagBlood="0" triggerFlagDistance="0" />
<BattleFlag flagId="607" forwardFlagId="1" triggerMode="0" x="53.73742" y="5.919054" z="-93.91866" rx="0" ry="351.9949" rz="0" cx="1" cy="1" cz="1" triggerCount="10" triggerFunc="2" willRelive="0" dieable="1" accountable="1" hideInDrama="0" hideWithDramable="0" guideId="0" hintLabelId="0" showOnUI="0" groupId="0" nodeSkill="0" alarmPosition="0,0,0" hoverPath="" triggerFlagEye2eye="601,602,603,604,605,606,607,608,609,610" triggerFlagEnter="0" triggerFlagAttack="0" triggerFlagKill="0" triggerFlagBlood="0" triggerFlagDistance="0" />
<BattleFlag flagId="608" forwardFlagId="1" triggerMode="0" x="56.43396" y="5.964293" z="-88.34641" rx="0" ry="351.9949" rz="0" cx="1" cy="1" cz="1" triggerCount="10" triggerFunc="2" willRelive="0" dieable="1" accountable="1" hideInDrama="0" hideWithDramable="0" guideId="0" hintLabelId="0" showOnUI="0" groupId="0" nodeSkill="0" alarmPosition="0,0,0" hoverPath="" triggerFlagEye2eye="601,602,603,604,605,606,607,608,609,610" triggerFlagEnter="0" triggerFlagAttack="0" triggerFlagKill="0" triggerFlagBlood="0" triggerFlagDistance="0" />
<BattleFlag flagId="609" forwardFlagId="1" triggerMode="0" x="47.88014" y="5.979382" z="-97.59103" rx="0" ry="351.9949" rz="0" cx="1" cy="1" cz="1" triggerCount="10" triggerFunc="2" willRelive="0" dieable="1" accountable="1" hideInDrama="0" hideWithDramable="0" guideId="0" hintLabelId="0" showOnUI="0" groupId="0" nodeSkill="0" alarmPosition="0,0,0" hoverPath="" triggerFlagEye2eye="601,602,603,604,605,606,607,608,609,610" triggerFlagEnter="0" triggerFlagAttack="0" triggerFlagKill="0" triggerFlagBlood="0" triggerFlagDistance="0" />
<BattleFlag flagId="610" forwardFlagId="1" triggerMode="0" x="43.78797" y="5.979382" z="-95.96304" rx="0" ry="351.9949" rz="0" cx="1" cy="1" cz="1" triggerCount="10" triggerFunc="2" willRelive="0" dieable="1" accountable="1" hideInDrama="0" hideWithDramable="0" guideId="0" hintLabelId="0" showOnUI="0" groupId="0" nodeSkill="0" alarmPosition="0,0,0" hoverPath="" triggerFlagEye2eye="601,602,603,604,605,606,607,608,609,610" triggerFlagEnter="0" triggerFlagAttack="0" triggerFlagKill="0" triggerFlagBlood="0" triggerFlagDistance="0" />
<BattleFlag flagId="2001" forwardFlagId="2" triggerMode="0" x="32.27248" y="5.661629" z="-78.1227" rx="0" ry="116.3101" rz="0" cx="1" cy="1" cz="1" triggerCount="10" triggerFunc="2" willRelive="0" dieable="0" accountable="0" hideInDrama="0" hideWithDramable="0" guideId="0" hintLabelId="0" showOnUI="0" groupId="0" nodeSkill="0" alarmPosition="0,0,0" hoverPath="" triggerFlagEye2eye="0" triggerFlagEnter="0" triggerFlagAttack="0" triggerFlagKill="0" triggerFlagBlood="0" triggerFlagDistance="0" />
<BattleFlag flagId="2002" forwardFlagId="1" triggerMode="0" x="40.93249" y="8.801628" z="-70.48271" rx="0" ry="116.3101" rz="0" cx="1" cy="1" cz="1" triggerCount="10" triggerFunc="2" willRelive="0" dieable="0" accountable="0" hideInDrama="0" hideWithDramable="0" guideId="0" hintLabelId="0" showOnUI="0" groupId="0" nodeSkill="0" alarmPosition="0,0,0" hoverPath="" triggerFlagEye2eye="0" triggerFlagEnter="0" triggerFlagAttack="0" triggerFlagKill="0" triggerFlagBlood="0" triggerFlagDistance="0" />
<BattleFlag flagId="1001" forwardFlagId="1" triggerMode="0" x="23.67857" y="5.939398" z="-118.2986" rx="0" ry="18.57491" rz="0" cx="35" cy="3.712439" cz="1" triggerCount="10" triggerFunc="1" willRelive="0" dieable="1" accountable="1" hideInDrama="0" hideWithDramable="0" guideId="0" hintLabelId="0" showOnUI="0" groupId="0" nodeSkill="0" alarmPosition="0,0,0" hoverPath="" triggerFlagEye2eye="0" triggerFlagEnter="0" triggerFlagAttack="0" triggerFlagKill="0" triggerFlagBlood="0" triggerFlagDistance="0" />
<BattleFlag flagId="1002" forwardFlagId="1" triggerMode="0" x="15.67748" y="6.662657" z="-74.6172" rx="0" ry="328.0549" rz="0" cx="30" cy="3.712441" cz="1.00063" triggerCount="-99" triggerFunc="1" willRelive="0" dieable="1" accountable="1" hideInDrama="0" hideWithDramable="0" guideId="0" hintLabelId="0" showOnUI="0" groupId="0" nodeSkill="0" alarmPosition="0,0,0" hoverPath="" triggerFlagEye2eye="0" triggerFlagEnter="0" triggerFlagAttack="0" triggerFlagKill="0" triggerFlagBlood="0" triggerFlagDistance="0" />
</dataset>
